clusterdb
