Metadata-Version: 2.1
Name: ClusterDB
Version: 20231221
Summary: Highly Available key value store for atomic updates - Replicated and Strongly Consistent
Home-page: https://github.com/magicray/ConfDB
Author: Bhupendra Singh
Author-email: bhsingh@gmail.com
Keywords: paxos,consistent,replicated,config
License-File: LICENSE
